LICENSE
pyproject.toml
docs/README.md
src/aiod/__init__.py
src/aiod/__version__.py
src/aiod/authentication/__init__.py
src/aiod/authentication/authentication.py
src/aiod/calls/__init__.py
src/aiod/calls/calls.py
src/aiod/calls/urls.py
src/aiod/calls/utils.py
src/aiod/configuration/__init__.py
src/aiod/configuration/_config.py
src/aiod/default/counts.py
src/aiod/resources/__init__.py
src/aiod/resources/case_studies.py
src/aiod/resources/computational_assets.py
src/aiod/resources/contacts.py
src/aiod/resources/datasets.py
src/aiod/resources/educational_resources.py
src/aiod/resources/events.py
src/aiod/resources/experiments.py
src/aiod/resources/ml_models.py
src/aiod/resources/news.py
src/aiod/resources/organisations.py
src/aiod/resources/persons.py
src/aiod/resources/platforms.py
src/aiod/resources/projects.py
src/aiod/resources/publications.py
src/aiod/resources/services.py
src/aiod/resources/teams.py
src/aiondemand.egg-info/PKG-INFO
src/aiondemand.egg-info/SOURCES.txt
src/aiondemand.egg-info/dependency_links.txt
src/aiondemand.egg-info/entry_points.txt
src/aiondemand.egg-info/requires.txt
src/aiondemand.egg-info/top_level.txt
tests/test_authentication.py
tests/test_counts.py
tests/test_endpoints.py