Metadata-Version: 2.1
Name: aiondemand
Version: 0.1.0b1
Summary: Python SDK for the AIoD metadata catalogue
Author-email: Jean Matias <smatias.jean@gmail.com>, Pieter Gijsbers <p.gijsbers@tue.nl>
Requires-Python: >=3.10
License-File: LICENSE
Requires-Dist: aiohttp
Requires-Dist: pandas
Requires-Dist: python-keycloak
Requires-Dist: requests
Provides-Extra: dev
Requires-Dist: pre-commit; extra == "dev"
Requires-Dist: responses; extra == "dev"
Requires-Dist: aioresponses; extra == "dev"
Requires-Dist: pytest; extra == "dev"
Requires-Dist: pytest-asyncio; extra == "dev"
Provides-Extra: doc
Requires-Dist: mkdocs-material; extra == "doc"
Requires-Dist: mkdocstrings-python; extra == "doc"
Requires-Dist: mkdocs-jupyter; extra == "doc"
Requires-Dist: griffe<1.0; extra == "doc"
